[
  1,
  [
    {
      "adult": false,
      "backdrop_path": "/uU1Mt4JWhDvl4vKb3AfxNsorkoM.jpg",
      "genre_ids": [
        10751,
        14,
        10749
      ],
      "id": 321612,
      "original_language": "en",
      "original_title": "Beauty and the Beast",
      "overview": "A live-action adaptation of Disney's version of the classic tale of a cursed prince and a beautiful young woman who helps him break the spell.",
      "popularity": 101.828,
      "poster_path": "/hKegSKIDep2ewJWPUQD7u0KqFIp.jpg",
      "release_date": "2017-03-16",
      "title": "Beauty and the Beast",
      "video": false,
      "vote_average": 7.0,
      "vote_count": 15600
    },
    {
      "adult": false,
      "backdrop_path": "/7t7IQhdA5rO8jhinE3ig258hqlf.jpg",
      "genre_ids": [
        10749,
        35,
        14,
        27
      ],
      "id": 988402,
      "original_language": "fr",
      "original_title": "Vampire humaniste cherche suicidaire consentant",
      "overview": "Sasha is a young vampire with a serious problem: she's too sensitive to kill. When her exasperated parents cut off her blood supply, Sasha's life is in jeopardy. Luckily, she meets Paul, a lonely teenager with suicidal tendencies who is willing to give his life to save hers. But their friendly agreement soon becomes a nocturnal quest to fulfill Paul's last wishes before day breaks.",
      "popularity": 39.1595,
      "poster_path": "/m5OItLBY5T38ew1YI4VSIXjl5G2.jpg",
      "release_date": "2023-10-13",
      "title": "Humanist Vampire Seeking Consenting Suicidal Person",
      "video": false,
      "vote_average": 7.4,
      "vote_count": 251
    },
    {
      "adult": false,
      "backdrop_path": "/uKb22E0nlzr914bA9KyA5CVCOlV.jpg",
      "genre_ids": [
        18,
        10749,
        14
      ],
      "id": 402431,
      "original_language": "en",
      "original_title": "Wicked",
      "overview": "In the land of Oz, ostracized and misunderstood green-skinned Elphaba is forced to share a room with the popular aristocrat Glinda at Shiz University, and the two's unlikely friendship is tested as they begin to fulfill their respective destinies as Glinda the Good and the Wicked Witch of the West.",
      "popularity": 32.3488,
      "poster_path": "/xDGbZ0JJ3mYaGKy4Nzd9Kph6M9L.jpg",
      "release_date": "2024-11-20",
      "title": "Wicked",
      "video": false,
      "vote_average": 6.9,
      "vote_count": 2081
    },
    {
      "adult": false,
      "backdrop_path": "/weAYfu6FfrNxEDJ3xH1XpgQcqUv.jpg",
      "genre_ids": [
        14,
        18,
        10749
      ],
      "id": 8966,
      "original_language": "en",
      "original_title": "Twilight",
      "overview": "When Bella Swan moves to a small town in the Pacific Northwest, she falls in love with Edward Cullen, a mysterious classmate who reveals himself to be a 108-year-old vampire. Despite Edward's repeated cautions, Bella can't stay away from him, a fatal move that endangers her own life.",
      "popularity": 27.4479,
      "poster_path": "/3Gkb6jm6962ADUPaCBqzz9CTbn9.jpg",
      "release_date": "2008-11-20",
      "title": "Twilight",
      "video": false,
      "vote_average": 6.288,
      "vote_count": 13767
    },
    {
      "adult": false,
      "backdrop_path": "/6YInbRTk39ckuLYFmUgBCKcKNjb.jpg",
      "genre_ids": [
        16,
        35,
        10751,
        14,
        10749
      ],
      "id": 976573,
      "original_language": "en",
      "original_title": "Elemental",
      "overview": "In a city where fire, water, land and air residents live together, a fiery young woman and a go-with-the-flow guy will discover something elemental: how much they have in common.",
      "popularity": 23.9617,
      "poster_path": "/4Y1WNkd88JXmGfhtWR7dmDAo1T2.jpg",
      "release_date": "2023-06-14",
      "title": "Elemental",
      "video": false,
      "vote_average": 7.6,
      "vote_count": 4777
    },
    {
      "adult": false,
      "backdrop_path": "/hjm1i9ZyueTaw7xCcpJmjKpb8Sv.jpg",
      "genre_ids": [
        16,
        36,
        28,
        18,
        14,
        10749
      ],
      "id": 483456,
      "original_language": "ja",
      "original_title": "PEACE MAKER 鐵 前篇 想道~オモウミチ~",
      "overview": "Although traumatized by witnessing the murder of his parents by one of the Choushuu, Ichimura Tetsunosuke's thirst for revenge leads him to desire strength. At the age of 15, Tetsunosuke approached the Shinsengumi, wanting to become one of its members. However, Tetsunosuke lacked the skill, mind, and will to emotionlessly cut down whoever threatened peace and the Shinsengumi. Even with the support of his brother Tatsunosuke and his newfound friends of the Shinsengumi, little did Tetsunosuke know the blood and pain he would have to face being part of this historical group.",
      "popularity": 22.6692,
      "poster_path": "/wbyIM5s7ZgwOmXycjBttBhhXtTq.jpg",
      "release_date": "2018-06-02",
      "title": "Peacemaker Kurogane: Belief",
      "video": false,
      "vote_average": 5.125,
      "vote_count": 4
    },
    {
      "adult": false,
      "backdrop_path": "/d1YxrmqIzS30haejpT7DcJMz3Md.jpg",
      "genre_ids": [
        18,
        10749,
        14
      ],
      "id": 1059372,
      "original_language": "id",
      "original_title": "Dear David",
      "overview": "A secret fantasy blog might jeopardize the promising future of Laras, a talented student, when the blog is revealed to her entire school.",
      "popularity": 21.1329,
      "poster_path": "/Ab1OedAN42deqjIkOu7X94nJwkG.jpg",
      "release_date": "2023-02-09",
      "title": "Dear David",
      "video": false,
      "vote_average": 6.097,
      "vote_count": 36
    },
    {
      "adult": false,
      "backdrop_path": "/qkl57wzSFrpi2sRpoc2mZJbMuLP.jpg",
      "genre_ids": [
        12,
        14,
        18,
        10749
      ],
      "id": 50620,
      "original_language": "en",
      "original_title": "The Twilight Saga: Breaking Dawn - Part 2",
      "overview": "After the birth of Renesmee, the Cullens gather other vampire clans in order to protect the child from a false allegation that puts the family in front of the Volturi.",
      "popularity": 20.1643,
      "poster_path": "/7IGdPaKujv0BjI0Zd0m0a4CzEjJ.jpg",
      "release_date": "2012-11-13",
      "title": "The Twilight Saga: Breaking Dawn - Part 2",
      "video": false,
      "vote_average": 6.462,
      "vote_count": 9020
    },
    {
      "adult": false,
      "backdrop_path": "/2fswjyrY3GEzeoVn6mF8pNeNcgf.jpg",
      "genre_ids": [
        18,
        14,
        10749
      ],
      "id": 4922,
      "original_language": "en",
      "original_title": "The Curious Case of Benjamin Button",
      "overview": "Born under unusual circumstances, Benjamin Button springs into being as an elderly man in a New Orleans nursing home and ages in reverse. Twelve years after his birth, he meets Daisy, a child who flits in and out of his life as she grows up to be a dancer. Though he has all sorts of unusual adventures over the course of his life, it is his relationship with Daisy, and the hope that they will come together at the right time, that drives Benjamin forward.",
      "popularity": 18.142,
      "poster_path": "/26wEWZYt6yJkwRVkjcbwJEFh9IS.jpg",
      "release_date": "2008-12-25",
      "title": "The Curious Case of Benjamin Button",
      "video": false,
      "vote_average": 7.591,
      "vote_count": 13035
    },
    {
      "adult": false,
      "backdrop_path": "/iEFuHjqrE059SmflBva1JzDJutE.jpg",
      "genre_ids": [
        16,
        14,
        28,
        10749,
        10751
      ],
      "id": 496450,
      "original_language": "fr",
      "original_title": "Miraculous - le film",
      "overview": "After a guardian of magical jewels turns an awkward girl and a popular boy into superheroes, they can never reveal their identities — even to each other.",
      "popularity": 18.0867,
      "poster_path": "/dQNJ8SdCMn3zWwHzzQD2xrphR1X.jpg",
      "release_date": "2023-07-05",
      "title": "Miraculous: Ladybug & Cat Noir, The Movie",
      "video": false,
      "vote_average": 7.643,
      "vote_count": 898
    },
    {
      "adult": false,
      "backdrop_path": "/o67MmFburfckl6iPa4DVkranLi3.jpg",
      "genre_ids": [
        14,
        18,
        10749
      ],
      "id": 297,
      "original_language": "en",
      "original_title": "Meet Joe Black",
      "overview": "William Parrish, media tycoon and loving father, is about to celebrate his 65th birthday. One morning, he is contacted by the inevitable, by hallucination, as he thinks. Later, Death enters his home and his life, personified in human form as Joe Black. His intention was to take William with him, but accidentally, Joe and William's beautiful daughter Susan have already met. Joe begins to develop certain interest in life on Earth, as well as in Susan, who has no clue with whom she's flirting.",
      "popularity": 18.011,
      "poster_path": "/fDPAjvfPMomkKF7cMRmL5Anak61.jpg",
      "release_date": "1998-11-12",
      "title": "Meet Joe Black",
      "video": false,
      "vote_average": 7.348,
      "vote_count": 5342
    },
    {
      "adult": false,
      "backdrop_path": "/hBwDYiOPwXHuwiYGP82ekFNSeBr.jpg",
      "genre_ids": [
        12,
        14,
        10749
      ],
      "id": 50619,
      "original_language": "en",
      "original_title": "The Twilight Saga: Breaking Dawn - Part 1",
      "overview": "Bella Swan and Edward Cullen's honeymoon phase is abruptly disrupted by betrayals and unforeseen tragedies that endanger their world.",
      "popularity": 17.6572,
      "poster_path": "/qs8LsHKYlVRmJbFUiSUhhRAygwj.jpg",
      "release_date": "2011-11-16",
      "title": "The Twilight Saga: Breaking Dawn - Part 1",
      "video": false,
      "vote_average": 6.196,
      "vote_count": 8898
    },
    {
      "adult": false,
      "backdrop_path": "/v23fWgJUEt8EMmvn19btIacxP8E.jpg",
      "genre_ids": [
        10749,
        14,
        16
      ],
      "id": 3933,
      "original_language": "en",
      "original_title": "Corpse Bride",
      "overview": "In a 19th-century European village, a young man about to be married is whisked away to the underworld and wed to a mysterious corpse bride, while his real bride waits bereft in the land of the living.",
      "popularity": 17.6526,
      "poster_path": "/isb2Qow76GpqYmsSyfdMfsYAjts.jpg",
      "release_date": "2005-09-12",
      "title": "Corpse Bride",
      "video": false,
      "vote_average": 7.579,
      "vote_count": 9516
    },
    {
      "adult": false,
      "backdrop_path": "/80uHK2xWwjlOxmfJ1wQB09omAht.jpg",
      "genre_ids": [
        10749,
        35,
        80,
        14
      ],
      "id": 854,
      "original_language": "en",
      "original_title": "The Mask",
      "overview": "When timid bank clerk Stanley Ipkiss discovers a magical mask containing the spirit of the Norse god Loki, his entire life changes. While wearing the mask, Ipkiss becomes a supernatural playboy exuding charm and confidence which allows him to catch the eye of local nightclub singer Tina Carlyle. Unfortunately, under the mask's influence, Ipkiss also robs a bank, which angers junior crime lord Dorian Tyrell, whose goons get blamed for the heist.",
      "popularity": 17.1977,
      "poster_path": "/xbbXp9px4o8Oe7IbGd0yIbla8mZ.jpg",
      "release_date": "1994-07-29",
      "title": "The Mask",
      "video": false,
      "vote_average": 6.961,
      "vote_count": 10530
    },
    {
      "adult": false,
      "backdrop_path": "/5OeY4U2rzePxWq2rkqMajUx2gz7.jpg",
      "genre_ids": [
        16,
        10751,
        12,
        14,
        10749
      ],
      "id": 812,
      "original_language": "en",
      "original_title": "Aladdin",
      "overview": "In the boorish city of Agrabah, kind-hearted street urchin Aladdin and Princess Jasmine fall in love, although she can only marry a prince. He and power-hungry Grand Vizier Jafar vie for a magic lamp that can fulfill their wishes.",
      "popularity": 16.2057,
      "poster_path": "/eLFfl7vS8dkeG1hKp5mwbm37V83.jpg",
      "release_date": "1992-11-25",
      "title": "Aladdin",
      "video": false,
      "vote_average": 7.651,
      "vote_count": 11434
    },
    {
      "adult": false,
      "backdrop_path": "/9iMCwIdz2ZXAuKurdPiVrJy05Kb.jpg",
      "genre_ids": [
        12,
        18,
        10749,
        14
      ],
      "id": 78698,
      "original_language": "en",
      "original_title": "Big Miracle",
      "overview": "A small-town news reporter and a Greenpeace volunteer enlist the help of rival superpowers to save three majestic gray whales trapped under the ice of the Arctic Circle.",
      "popularity": 16.1199,
      "poster_path": "/hqdrgC5oHK06DDaAlulReUC7Nog.jpg",
      "release_date": "2012-02-02",
      "title": "Big Miracle",
      "video": false,
      "vote_average": 6.689,
      "vote_count": 499
    },
    {
      "adult": false,
      "backdrop_path": "/8I9nnpZNjjP9J2ZPpg3DP94mX2U.jpg",
      "genre_ids": [
        16,
        18,
        10749,
        14,
        878
      ],
      "id": 916192,
      "original_language": "ja",
      "original_title": "夏へのトンネル、さよならの出口",
      "overview": "Urashima Tunnel – Once you enter that tunnel, you can get whatever you want, but at a price. Kaoru Tohno, who seems to have an elusive personality and traumatic past, and Anzu Hanashiro, who is struggling to reconcile her ideal image and true-to-heart attitude, team up to investigate the Urashima Tunnel and get what they want. This is an unforgettable summer story of nostalgia and sprinting in a remote countryside.",
      "popularity": 15.4008,
      "poster_path": "/5AGA6pbBKXZTI8k1c6odx30JuQR.jpg",
      "release_date": "2022-09-09",
      "title": "The Tunnel to Summer, the Exit of Goodbyes",
      "video": false,
      "vote_average": 7.726,
      "vote_count": 208
    },
    {
      "adult": false,
      "backdrop_path": "/q7vmCCmyiHnuKGMzHZlr0fD44b9.jpg",
      "genre_ids": [
        10749,
        14,
        10751,
        18
      ],
      "id": 150689,
      "original_language": "en",
      "original_title": "Cinderella",
      "overview": "When her father unexpectedly passes away, young Ella finds herself at the mercy of her cruel stepmother and her daughters. Never one to give up hope, Ella's fortunes begin to change after meeting a dashing stranger in the woods.",
      "popularity": 15.2896,
      "poster_path": "/j91LJmcWo16CArFOoapsz84bwxb.jpg",
      "release_date": "2015-03-06",
      "title": "Cinderella",
      "video": false,
      "vote_average": 6.825,
      "vote_count": 7149
    },
    {
      "adult": false,
      "backdrop_path": "/lAs4Y5a8Pi86xDwuv8cx2prOVI2.jpg",
      "genre_ids": [
        12,
        10751,
        14,
        10749
      ],
      "id": 447277,
      "original_language": "en",
      "original_title": "The Little Mermaid",
      "overview": "The youngest of King Triton’s daughters, and the most defiant, Ariel longs to find out more about the world beyond the sea, and while visiting the surface, falls for the dashing Prince Eric. With mermaids forbidden to interact with humans, Ariel makes a deal with the evil sea witch, Ursula, which gives her a chance to experience life on land, but ultimately places her life – and her father’s crown – in jeopardy.",
      "popularity": 14.6583,
      "poster_path": "/ym1dxyOk4jFcSl4Q2zmRrA5BEEN.jpg",
      "release_date": "2023-05-18",
      "title": "The Little Mermaid",
      "video": false,
      "vote_average": 6.3,
      "vote_count": 3047
    },
    {
      "adult": false,
      "backdrop_path": "/puJKgNcWaGgMk5VHanSSomUTpmw.jpg",
      "genre_ids": [
        10751,
        14,
        16,
        10749
      ],
      "id": 11224,
      "original_language": "en",
      "original_title": "Cinderella",
      "overview": "Cinderella has faith her dreams of a better life will come true. With help from her loyal mice friends and a wave of her Fairy Godmother's wand, Cinderella's rags are magically turned into a glorious gown and off she goes to the Royal Ball. But when the clock strikes midnight, the spell is broken, leaving a single glass slipper... the only key to the ultimate fairy-tale ending!",
      "popularity": 14.6109,
      "poster_path": "/4nssBcQUBadCTBjrAkX46mVEKts.jpg",
      "release_date": "1950-02-22",
      "title": "Cinderella",
      "video": false,
      "vote_average": 7.0,
      "vote_count": 6824
    }
  ],
  109,
  2168,
  2,
  [
    {
      "adult": false,
      "backdrop_path": "/dOeaWGpouIaONuhRKOj2SrTEWe7.jpg",
      "genre_ids": [
        35,
        10751,
        14,
        10749
      ],
      "id": 4523,
      "original_language": "en",
      "original_title": "Enchanted",
      "overview": "The beautiful princess Giselle is banished by an evil queen from her magical, musical animated land and finds herself in the gritty reality of the streets of modern-day Manhattan. Shocked by this strange new environment that doesn't operate on a \"happily ever after\" basis, Giselle is now adrift in a chaotic world badly in need of enchantment. But when Giselle begins to fall in love with a charmingly flawed divorce lawyer who has come to her aid - even though she is already promised to a perfect fairy tale prince back home - she has to wonder: Can a storybook view of romance survive in the real world?",
      "popularity": 14.9154,
      "poster_path": "/8KCNzCArLlvLdQoHx6npua2VSVc.jpg",
      "release_date": "2007-11-20",
      "title": "Enchanted",
      "video": false,
      "vote_average": 6.8,
      "vote_count": 5476
    },
    {
      "adult": false,
      "backdrop_path": "/jsgRkhPxYtzAhDFCUyNbvlX63tY.jpg",
      "genre_ids": [
        10749,
        10751,
        16,
        14
      ],
      "id": 10020,
      "original_language": "en",
      "original_title": "Beauty and the Beast",
      "overview": "Follow the adventures of Belle, a bright young woman who finds herself in the castle of a prince who's been turned into a mysterious beast. With the help of the castle's enchanted staff, Belle soon learns the most important lesson of all -- that true beauty comes from within.",
      "popularity": 13.9118,
      "poster_path": "/hUJ0UvQ5tgE2Z9WpfuduVSdiCiU.jpg",
      "release_date": "1991-10-22",
      "title": "Beauty and the Beast",
      "video": false,
      "vote_average": 7.731,
      "vote_count": 10115
    },
    {
      "adult": false,
      "backdrop_path": "/4hfcpHmMEgmFTdnVx4XCtM6dgCG.jpg",
      "genre_ids": [
        14,
        12,
        28,
        10751,
        10749
      ],
      "id": 102651,
      "original_language": "en",
      "original_title": "Maleficent",
      "overview": "A beautiful, pure-hearted young woman, Maleficent has an idyllic life growing up in a peaceable forest kingdom, until one day when an invading army threatens the harmony of the land. She rises to be the land's fiercest protector, but she ultimately suffers a ruthless betrayal – an act that begins to turn her heart into stone. Bent on revenge, Maleficent faces an epic battle with the invading King's successor and, as a result, places a curse upon his newborn infant Aurora. As the child grows, Maleficent realizes that Aurora holds the key to peace in the kingdom – and to Maleficent's true happiness as well.",
      "popularity": 12.6928,
      "poster_path": "/bDG3yei6AJlEAK3A5wN7RwFXQ7V.jpg",
      "release_date": "2014-05-28",
      "title": "Maleficent",
      "video": false,
      "vote_average": 7.088,
      "vote_count": 13267
    },
    {
      "adult": false,
      "backdrop_path": "/8yjHiSuSEhzR916LcIecuQ8tETG.jpg",
      "genre_ids": [
        10749,
        18,
        14
      ],
      "id": 994108,
      "original_language": "en",
      "original_title": "All of Us Strangers",
      "overview": "One night in his near-empty tower block in contemporary London, Adam has a chance encounter with a mysterious neighbor Harry, which punctures the rhythm of his everyday life.",
      "popularity": 12.2603,
      "poster_path": "/aviJMFZSnnCAsCVyJGaPNx4Ef3i.jpg",
      "release_date": "2023-12-22",
      "title": "All of Us Strangers",
      "video": false,
      "vote_average": 7.452,
      "vote_count": 834
    },
    {
      "adult": false,
      "backdrop_path": "/jFK8BOPL6ZeWyjMVWX8ajsTTinp.jpg",
      "genre_ids": [
        16,
        18,
        14,
        10749
      ],
      "id": 568160,
      "original_language": "ja",
      "original_title": "天気の子",
      "overview": "The summer of his high school freshman year, Hodaka runs away from his remote island home to Tokyo, and quickly finds himself pushed to his financial and personal limits. The weather is unusually gloomy and rainy every day, as if taking its cue from his life. After many days of solitude, he finally finds work as a freelance writer for a mysterious occult magazine. Then, one day, Hodaka meets Hina on a busy street corner. This bright and strong-willed girl possesses a strange and wonderful ability: the power to stop the rain and clear the sky.",
      "popularity": 13.0714,
      "poster_path": "/qgrk7r1fV4IjuoeiGS5HOhXNdLJ.jpg",
      "release_date": "2019-06-19",
      "title": "Weathering with You",
      "video": false,
      "vote_average": 8.002,
      "vote_count": 2385
    },
    {
      "adult": false,
      "backdrop_path": "/y5tad0a4yRbxYgOHGllEIEeCCKt.jpg",
      "genre_ids": [
        16,
        10749,
        14,
        10751
      ],
      "id": 10198,
      "original_language": "en",
      "original_title": "The Princess and the Frog",
      "overview": "A waitress, desperate to fulfill her dreams as a restaurant owner, is set on a journey to turn a frog prince back into a human being, but she has to face the same problem after she kisses him.",
      "popularity": 13.2587,
      "poster_path": "/v6nAUs62OJ4DXmnnmPFeVmMz8H9.jpg",
      "release_date": "2009-12-08",
      "title": "The Princess and the Frog",
      "video": false,
      "vote_average": 7.22,
      "vote_count": 5756
    },
    {
      "adult": false,
      "backdrop_path": "/fzZmcKQv7ZTGIiPvocPhNs3wUyK.jpg",
      "genre_ids": [
        18,
        10749,
        14
      ],
      "id": 122906,
      "original_language": "en",
      "original_title": "About Time",
      "overview": "The night after another unsatisfactory New Year's party, Tim's father tells his son that the men in his family have always had the ability to travel through time. They can't change history, but they can change what happens and has happened in their own lives. Thus begins the start of a lesson in learning to appreciate life itself as it is, as it comes, and most importantly, the people living alongside us.",
      "popularity": 12.5472,
      "poster_path": "/iR1bVfURbN7r1C46WHFbwCkVve.jpg",
      "release_date": "2013-09-04",
      "title": "About Time",
      "video": false,
      "vote_average": 7.915,
      "vote_count": 8715
    },
    {
      "adult": false,
      "backdrop_path": "/3Nn5BOM1EVw1IYrv6MsbOS6N1Ol.jpg",
      "genre_ids": [
        14,
        18,
        10749
      ],
      "id": 162,
      "original_language": "en",
      "original_title": "Edward Scissorhands",
      "overview": "A small suburban town receives a visit from a castaway unfinished science experiment named Edward.",
      "popularity": 12.1927,
      "poster_path": "/e0FqKFvGPdQNWG8tF9cZBtev9Em.jpg",
      "release_date": "1990-12-07",
      "title": "Edward Scissorhands",
      "video": false,
      "vote_average": 7.716,
      "vote_count": 13121
    },
    {
      "adult": false,
      "backdrop_path": "/rVqY0Bo4Npf6EIONUROxjYAJfmD.jpg",
      "genre_ids": [
        12,
        14,
        10749,
        10751
      ],
      "id": 420817,
      "original_language": "en",
      "original_title": "Aladdin",
      "overview": "A kindhearted street urchin named Aladdin embarks on a magical adventure after finding a lamp that releases a wisecracking genie while a power-hungry Grand Vizier vies for the same lamp that has the power to make their deepest wishes come true.",
      "popularity": 11.5959,
      "poster_path": "/ykUEbfpkf8d0w49pHh0AD2KrT52.jpg",
      "release_date": "2019-05-22",
      "title": "Aladdin",
      "video": false,
      "vote_average": 7.097,
      "vote_count": 10208
    },
    {
      "adult": false,
      "backdrop_path": "/5yGgVqsk3v44jfGVuFWIDxOExIF.jpg",
      "genre_ids": [
        18,
        14,
        10749
      ],
      "id": 399055,
      "original_language": "en",
      "original_title": "The Shape of Water",
      "overview": "An other-worldly story, set against the backdrop of Cold War era America circa 1962, where a mute janitor working at a lab falls in love with an amphibious man being held captive there and devises a plan to help him escape.",
      "popularity": 11.5474,
      "poster_path": "/9zfwPffUXpBrEP26yp0q1ckXDcj.jpg",
      "release_date": "2017-12-01",
      "title": "The Shape of Water",
      "video": false,
      "vote_average": 7.242,
      "vote_count": 12302
    },
    {
      "adult": false,
      "backdrop_path": "/oG9dcGSSu13fjFp1Uly15ZXjRKV.jpg",
      "genre_ids": [
        16,
        10751,
        14,
        12,
        35,
        10749
      ],
      "id": 11970,
      "original_language": "en",
      "original_title": "Hercules",
      "overview": "Bestowed with superhuman strength, a young mortal named Hercules sets out to prove himself a hero in the eyes of his father, the great god Zeus. Along with his friends Pegasus, a flying horse, and Phil, a personal trainer, Hercules is tricked by the hilarious, hotheaded villain Hades, who's plotting to take over Mount Olympus!",
      "popularity": 11.9397,
      "poster_path": "/dK9rNoC97tgX3xXg5zdxFisdfcp.jpg",
      "release_date": "1997-06-13",
      "title": "Hercules",
      "video": false,
      "vote_average": 7.5,
      "vote_count": 7551
    },
    {
      "adult": false,
      "backdrop_path": "/sIJTdyF6JFbIz5mENPpeSlCKYyB.jpg",
      "genre_ids": [
        14,
        35,
        10749
      ],
      "id": 59436,
      "original_language": "en",
      "original_title": "Midnight in Paris",
      "overview": "While on a trip to Paris with his fiancée's family, a nostalgic screenwriter finds himself mysteriously going back to the 1920s every day at midnight.",
      "popularity": 10.4067,
      "poster_path": "/4wBG5kbfagTQclETblPRRGihk0I.jpg",
      "release_date": "2011-05-11",
      "title": "Midnight in Paris",
      "video": false,
      "vote_average": 7.524,
      "vote_count": 7392
    },
    {
      "adult": false,
      "backdrop_path": "/eHTZoXmB4vnDqANZXPZcdAiYQo5.jpg",
      "genre_ids": [
        16,
        18,
        10749,
        14
      ],
      "id": 667520,
      "original_language": "ja",
      "original_title": "泣きたい私は猫をかぶる",
      "overview": "A peculiar girl transforms into a cat to catch her crush's attention. But before she realizes it, the line between human and animal starts to blur.",
      "popularity": 12.0582,
      "poster_path": "/6inkRM1XGBG5vRhclCPWfMenp7N.jpg",
      "release_date": "2020-06-18",
      "title": "A Whisker Away",
      "video": false,
      "vote_average": 7.902,
      "vote_count": 1405
    },
    {
      "adult": false,
      "backdrop_path": "/oguoQWtQJcqIkmmUNbe3CmLx6AP.jpg",
      "genre_ids": [
        12,
        14,
        18,
        10749
      ],
      "id": 24021,
      "original_language": "en",
      "original_title": "The Twilight Saga: Eclipse",
      "overview": "Bella once again finds herself surrounded by danger as Seattle is ravaged by a string of mysterious killings and a malicious vampire continues her quest for revenge. In the midst of it all, she is forced to choose between her love for Edward and her friendship with Jacob, knowing that her decision has the potential to ignite the ageless struggle between vampire and werewolf. With her graduation quickly approaching, Bella is confronted with the most important decision of her life.",
      "popularity": 10.6577,
      "poster_path": "/3mFM80dPzSqoXXuC2UMvLIRWX32.jpg",
      "release_date": "2010-06-23",
      "title": "The Twilight Saga: Eclipse",
      "video": false,
      "vote_average": 6.205,
      "vote_count": 8883
    },
    {
      "adult": false,
      "backdrop_path": "/jh6GJSeqyazoKfi3Lu19N1fvr7e.jpg",
      "genre_ids": [
        16,
        18,
        14,
        10749
      ],
      "id": 431819,
      "original_language": "ja",
      "original_title": "打ち上げ花火、下から見るか？横から見るか？",
      "overview": "Moshimo, Japan. The annual fireworks festival is about to take place and a group of schoolboys, arguing over whether they are round or flat when viewed from different angles, set out to find it out.",
      "popularity": 9.9064,
      "poster_path": "/ifm8CdFjYMfEq0bLT7XwJxjZmjO.jpg",
      "release_date": "2017-08-18",
      "title": "Fireworks",
      "video": false,
      "vote_average": 6.6,
      "vote_count": 345
    },
    {
      "adult": false,
      "backdrop_path": "/pYl4YpepgRbr504D7ep58C5gMyF.jpg",
      "genre_ids": [
        10749,
        18,
        14
      ],
      "id": 795,
      "original_language": "en",
      "original_title": "City of Angels",
      "overview": "When a guardian angel – who invisibly watches over the citizens of Los Angeles – becomes captivated by a strong-willed heart surgeon, he ponders trading in his pure, otherworldly existence for a mortal life with his beloved. The couple embarks on a tender but forbidden romance spanning heaven and Earth.",
      "popularity": 9.8786,
      "poster_path": "/iuzxpUjHsbQJXV3kB9ZAdCimM60.jpg",
      "release_date": "1998-04-10",
      "title": "City of Angels",
      "video": false,
      "vote_average": 6.805,
      "vote_count": 2184
    },
    {
      "adult": false,
      "backdrop_path": "/mGznDQ8opBuRd004ChVWhDqjAyW.jpg",
      "genre_ids": [
        10749,
        35,
        14
      ],
      "id": 6435,
      "original_language": "en",
      "original_title": "Practical Magic",
      "overview": "Sally and Gillian Owens, born into a magical family, have mostly avoided witchcraft themselves. But when Gillian's vicious boyfriend, Jimmy Angelov, dies unexpectedly, the Owens sisters give themselves a crash course in hard magic. With policeman Gary Hallet growing suspicious, the girls struggle to resurrect Angelov -- and unwittingly inject his corpse with an evil spirit that threatens to end their family line.",
      "popularity": 9.6996,
      "poster_path": "/AwmToSgf2IL3aHv0QRVsR5KvChv.jpg",
      "release_date": "1998-10-16",
      "title": "Practical Magic",
      "video": false,
      "vote_average": 6.794,
      "vote_count": 1561
    },
    {
      "adult": false,
      "backdrop_path": "/1E7kqUJghDRSgYkxDXAyoaVqQ96.jpg",
      "genre_ids": [
        12,
        14,
        18,
        10749
      ],
      "id": 18239,
      "original_language": "en",
      "original_title": "The Twilight Saga: New Moon",
      "overview": "Forks, Washington resident Bella Swan is reeling from the departure of her vampire love, Edward Cullen, and finds comfort in her friendship with Jacob Black, a werewolf. But before she knows it, she's thrust into a centuries-old conflict, and her desire to be with Edward at any cost leads her to take greater and greater risks.",
      "popularity": 8.2628,
      "poster_path": "/k2qTooPlHffgNABNWxeJdGMglPK.jpg",
      "release_date": "2009-11-18",
      "title": "The Twilight Saga: New Moon",
      "video": false,
      "vote_average": 5.992,
      "vote_count": 9345
    },
    {
      "adult": false,
      "backdrop_path": "/5om2iHhm2dgv0s2YgPDSEMIkRNx.jpg",
      "genre_ids": [
        35,
        14,
        10402,
        10749
      ],
      "id": 515195,
      "original_language": "en",
      "original_title": "Yesterday",
      "overview": "A struggling musician realizes he's the only person on Earth who can remember The Beatles after waking up in an alternate reality where the group was forgotten.",
      "popularity": 9.8636,
      "poster_path": "/9fYka5CQt9nrb6LOtKicysUf9NA.jpg",
      "release_date": "2019-06-26",
      "title": "Yesterday",
      "video": false,
      "vote_average": 6.697,
      "vote_count": 3992
    },
    {
      "adult": false,
      "backdrop_path": "/5MgMCnslrxQfOfaq6T5ndkLlcCk.jpg",
      "genre_ids": [
        16,
        10749,
        18,
        14
      ],
      "id": 572154,
      "original_language": "ja",
      "original_title": "青春ブタ野郎はゆめみる少女の夢を見ない",
      "overview": "In Fujisawa, Sakuta Azusagawa is in his second year of high school. Blissful days with his girlfriend and upperclassman, Mai Sakurajima, are interrupted by the appearance of his first crush, Shoko Makinohara.",
      "popularity": 9.331,
      "poster_path": "/AtFnN4OztDJy8IFwYd5JfU0jlEM.jpg",
      "release_date": "2019-06-15",
      "title": "Rascal Does Not Dream of a Dreaming Girl",
      "video": false,
      "vote_average": 8.244,
      "vote_count": 535
    }
  ],
  109,
  2168,
  3,
  [
    {
      "adult": false,
      "backdrop_path": "/aLqtWLA6NQHBwQHvHDq5z4EKUm0.jpg",
      "genre_ids": [
        16,
        14,
        10749,
        18
      ],
      "id": 533514,
      "original_language": "ja",
      "original_title": "劇場版 ヴァイオレット・エヴァーガーデン",
      "overview": "As the world moves on from the war and technological advances bring changes to her life, Violet still hopes to see her lost commanding officer again.",
      "popularity": 9.3912,
      "poster_path": "/A9R6bukzzRmOzxvDQsXdQpeNm8l.jpg",
      "release_date": "2020-09-18",
      "title": "Violet Evergarden: The Movie",
      "video": false,
      "vote_average": 8.3,
      "vote_count": 440
    },
    {
      "adult": false,
      "backdrop_path": "/7ZiMrbitgbyio4eOzFKRruPKu5G.jpg",
      "genre_ids": [
        14,
        10749,
        35
      ],
      "id": 593910,
      "original_language": "en",
      "original_title": "Cinderella",
      "overview": "Cinderella, an orphaned girl with an evil stepmother, has big dreams and with the help of her Fabulous Godmother, she perseveres to make them come true.",
      "popularity": 9.4482,
      "poster_path": "/clDFqATL4zcE7LzUwkrVj3zHvk7.jpg",
      "release_date": "2021-09-03",
      "title": "Cinderella",
      "video": false,
      "vote_average": 6.357,
      "vote_count": 1413
    },
    {
      "adult": false,
      "backdrop_path": "/JeEKrJUUT29gTsueHrqibGarCr.jpg",
      "genre_ids": [
        16,
        18,
        10749,
        14
      ],
      "id": 845387,
      "original_language": "ja",
      "original_title": "アリスとテレスのまぼろし工場",
      "overview": "A factory explosion plunges a small town into a timeless freeze, leaving teenage Masamune and his pals to grapple with a quickly collapsing reality.",
      "popularity": 9.667,
      "poster_path": "/7kzoPEasqFZGPGHj1imsLtTM20k.jpg",
      "release_date": "2023-09-15",
      "title": "maboroshi",
      "video": false,
      "vote_average": 7.349,
      "vote_count": 109
    },
    {
      "adult": false,
      "backdrop_path": "/nN4Gs3vZAOJ1D6FRtrwbU9VGYwU.jpg",
      "genre_ids": [
        16,
        14,
        10751,
        35,
        10749,
        12
      ],
      "id": 486589,
      "original_language": "en",
      "original_title": "Red Shoes and the Seven Dwarfs",
      "overview": "Princes who have been turned into Dwarfs seek the red shoes of a lady in order to break the spell, although it will not be easy.",
      "popularity": 11.2183,
      "poster_path": "/MBiKqTsouYqAACLYNDadsjhhC0.jpg",
      "release_date": "2019-07-25",
      "title": "Red Shoes and the Seven Dwarfs",
      "video": false,
      "vote_average": 7.727,
      "vote_count": 1097
    },
    {
      "adult": false,
      "backdrop_path": "/xfZ2u86Tui0aTKcPYcKGStzxWZv.jpg",
      "genre_ids": [
        28,
        16,
        18,
        14,
        10749
      ],
      "id": 283984,
      "original_language": "ja",
      "original_title": "劇場版「Fate/stay night [Heaven’s Feel]」Ⅰ.presage flower",
      "overview": "Shiro Emiya is a young magus who attends Homurahara Academy in Fuyuki City. One day after cleaning the Archery Dojo in his school, he catches a glimpse of a fight between superhuman beings, and he gets involved in the Holy Grail War, a ritual where magi called Masters fight each other with their Servants to win the Holy Grail. Shiro joins the battle to stop an evildoer from winning the Grail and to save innocent people, but everything goes wrong when a mysterious \"Shadow\" begins to indiscriminately kill people in Fuyuki...",
      "popularity": 8.5251,
      "poster_path": "/6nEtmBg07DA5BWjcrmD49rxHsVQ.jpg",
      "release_date": "2017-10-14",
      "title": "Fate/stay night: Heaven's Feel I. Presage Flower",
      "video": false,
      "vote_average": 7.487,
      "vote_count": 236
    },
    {
      "adult": false,
      "backdrop_path": "/15JUzyooElSbMXXYl2gnHX62A7X.jpg",
      "genre_ids": [
        18,
        10749,
        878,
        14
      ],
      "id": 9294,
      "original_language": "en",
      "original_title": "Phenomenon",
      "overview": "An ordinary man sees a bright light descend from the sky, and discovers he now has super-intelligence and telekinesis.",
      "popularity": 8.8229,
      "poster_path": "/5eK1HNf0Kl2vDPOeqf1kX4SKxrw.jpg",
      "release_date": "1996-07-05",
      "title": "Phenomenon",
      "video": false,
      "vote_average": 6.446,
      "vote_count": 1202
    },
    {
      "adult": false,
      "backdrop_path": "/k63j5qexRlpD3wxzETKfuZRVWiT.jpg",
      "genre_ids": [
        18,
        35,
        10749,
        14
      ],
      "id": 9007,
      "original_language": "en",
      "original_title": "Just Like Heaven",
      "overview": "Shortly after David Abbott moves into his new San Francisco digs, he has an unwelcome visitor on his hands: winsome Elizabeth Masterson, who asserts that the apartment is hers -- and promptly vanishes. When she starts appearing and disappearing at will, David thinks she's a ghost, while Elizabeth is convinced she's alive.",
      "popularity": 8.7074,
      "poster_path": "/2cLbyVNhEEaUJGg7rfbLtX6454I.jpg",
      "release_date": "2005-09-16",
      "title": "Just Like Heaven",
      "video": false,
      "vote_average": 6.962,
      "vote_count": 2406
    },
    {
      "adult": false,
      "backdrop_path": "/gnosJeDIDQXy9uDewXphEpDWNYT.jpg",
      "genre_ids": [
        35,
        18,
        10749,
        14
      ],
      "id": 5994,
      "original_language": "en",
      "original_title": "The Family Man",
      "overview": "Jack's lavish, fast-paced lifestyle changes one Christmas night when he stumbles into a grocery store holdup and disarms the gunman. The next morning he wakes up in bed lying next to Kate, his college sweetheart he left in order to pursue his career, and to the horrifying discovery that his former life no longer exists. As he stumbles through this alternate suburban universe, Jack finds himself at a crossroad where he must choose between his high-power career and the woman he loves.",
      "popularity": 8.4915,
      "poster_path": "/9wToOVsKuf0XeKhlauzCa3D8Gui.jpg",
      "release_date": "2000-12-12",
      "title": "The Family Man",
      "video": false,
      "vote_average": 6.8,
      "vote_count": 2024
    },
    {
      "adult": false,
      "backdrop_path": "/tLfQZkB4yBlO1h5WMIFLJgHYcZD.jpg",
      "genre_ids": [
        16,
        10749,
        14,
        28,
        18
      ],
      "id": 390635,
      "original_language": "ja",
      "original_title": "劇場版「Fate/stay night [Heaven’s Feel]」Ⅲ.spring song",
      "overview": "As Sakura drowns in the murky darkness of the sins she has committed, Shirou's vow to protect her at all costs leads him into a raging battle to put an end to the Holy Grail War.  Will Shirou's wish reach Sakura even as he challenges fate itself in a desperate battle against the rising tide?",
      "popularity": 8.8381,
      "poster_path": "/hIK5kEdFwOHnHTa06ntTVSfG9im.jpg",
      "release_date": "2020-08-15",
      "title": "Fate/stay night: Heaven's Feel III. Spring Song",
      "video": false,
      "vote_average": 7.738,
      "vote_count": 181
    },
    {
      "adult": false,
      "backdrop_path": "/ttBydD0SynC0TMkW3AcnmsySkLp.jpg",
      "genre_ids": [
        10749,
        14,
        18,
        35
      ],
      "id": 137,
      "original_language": "en",
      "original_title": "Groundhog Day",
      "overview": "A narcissistic TV weatherman, along with his attractive-but-distant producer, and his mawkish cameraman, is sent to report on Groundhog Day in the small town of Punxsutawney, where he finds himself repeating the same day over and over.",
      "popularity": 7.7271,
      "poster_path": "/gCgt1WARPZaXnq523ySQEUKinCs.jpg",
      "release_date": "1993-02-11",
      "title": "Groundhog Day",
      "video": false,
      "vote_average": 7.614,
      "vote_count": 8235
    },
    {
      "adult": false,
      "backdrop_path": "/Amvdexp1W0uqqSEkWlYjM9nDJfa.jpg",
      "genre_ids": [
        16,
        28,
        14,
        18,
        10749
      ],
      "id": 390634,
      "original_language": "ja",
      "original_title": "劇場版「Fate/stay night [Heaven’s Feel]」Ⅱ.lost butterfly",
      "overview": "The Fifth Holy Grail War continues, and the ensuing chaos results in higher stakes for all participants. Shirou Emiya continues to participate in the war, aspiring to be a hero of justice who saves everyone. He sets out in search of the truth behind a mysterious dark shadow and its murder spree, determined to defeat it.  Meanwhile, Shinji Matou sets his own plans into motion, threatening Shirou through his sister Sakura Matou. Shirou and Rin Tohsaka battle Shinji, hoping to relieve Sakura from the abuses of her brother. But the ugly truth of the Matou siblings begins to surface, and many dark secrets are exposed.",
      "popularity": 8.1241,
      "poster_path": "/nInpnGCjhzVhsASIUAmgM1QIhYM.jpg",
      "release_date": "2019-01-12",
      "title": "Fate/stay night: Heaven's Feel II. Lost Butterfly",
      "video": false,
      "vote_average": 7.002,
      "vote_count": 243
    },
    {
      "adult": false,
      "backdrop_path": "/snwkqb23cuMd0qY1MPffXWWBoZV.jpg",
      "genre_ids": [
        35,
        14,
        10749
      ],
      "id": 10096,
      "original_language": "en",
      "original_title": "13 Going on 30",
      "overview": "A girl who's sick of the social strictures of junior high is transformed into a grownup overnight. In this feel-good fairy tale, teenager Jenna wants a boyfriend, and when she's unable to find one, she fantasizes about being a well-adjusted adult. Suddenly, her secret desire becomes a reality, and she is transformed into a 30-year-old, but adulthood, with its own set of male-female challenges, isn't as easy as it looks.",
      "popularity": 7.9788,
      "poster_path": "/iNZdSIfhSCMtRILDNyhLn8UKeSG.jpg",
      "release_date": "2004-04-13",
      "title": "13 Going on 30",
      "video": false,
      "vote_average": 6.758,
      "vote_count": 5241
    },
    {
      "adult": false,
      "backdrop_path": "/vooRKLGVvFRFmx9swcMh26uYZSf.jpg",
      "genre_ids": [
        16,
        10749,
        35,
        18,
        14
      ],
      "id": 530079,
      "original_language": "ja",
      "original_title": "きみと、波にのれたら",
      "overview": "Hinako is a surf-loving college student who has just moved to a small seaside town. When a sudden fire breaks out at her apartment building, she is rescued by Minato, a handsome firefighter, and the two soon fall in love.",
      "popularity": 8.1618,
      "poster_path": "/byoY2stdullEcVjlaWs1ENXyrDm.jpg",
      "release_date": "2019-06-21",
      "title": "Ride Your Wave",
      "video": false,
      "vote_average": 7.596,
      "vote_count": 339
    },
    {
      "adult": false,
      "backdrop_path": "/4CryneVBqNPqmXR206snm7491gT.jpg",
      "genre_ids": [
        14,
        16,
        10749,
        10751
      ],
      "id": 10882,
      "original_language": "en",
      "original_title": "Sleeping Beauty",
      "overview": "Cursed to die by the evil fairy Maleficent when she was a baby, Princess Aurora is sent into hiding under protection from three good fairies. As she grows up far away, Maleficent becomes increasingly determined to seal the princess's fate.",
      "popularity": 7.7746,
      "poster_path": "/dK4OZwFFxnfK7MvqfVqw94mavL7.jpg",
      "release_date": "1959-02-17",
      "title": "Sleeping Beauty",
      "video": false,
      "vote_average": 6.9,
      "vote_count": 5223
    },
    {
      "adult": false,
      "backdrop_path": "/2CisgvF2HcIVnbMZbSjASCtSgEb.jpg",
      "genre_ids": [
        12,
        10751,
        14,
        35,
        10749
      ],
      "id": 2493,
      "original_language": "en",
      "original_title": "The Princess Bride",
      "overview": "In this enchantingly cracked fairy tale, the beautiful Princess Buttercup and the dashing Westley must overcome staggering odds to find happiness amid six-fingered swordsmen, murderous princes, Sicilians and rodents of unusual size. But even death can't stop these true lovebirds from triumphing.",
      "popularity": 7.8834,
      "poster_path": "/eOp2XmQpH6QYPfOVSQTSGoYABMc.jpg",
      "release_date": "1987-09-25",
      "title": "The Princess Bride",
      "video": false,
      "vote_average": 7.681,
      "vote_count": 4682
    },
    {
      "adult": false,
      "backdrop_path": "/qyOO0dgss0oeUYFPWbbdALDgOSm.jpg",
      "genre_ids": [
        12,
        28,
        14,
        878,
        53,
        10749,
        16
      ],
      "id": 2114,
      "original_language": "en",
      "original_title": "Final Fantasy: The Spirits Within",
      "overview": "Led by a strange dream, scientist Aki Ross struggles to collect the eight spirits in the hope of creating a force powerful enough to protect the planet. With the aid of the Deep Eyes Squadron and her mentor, Dr. Sid, Aki must save the Earth from its darkest hate and unleash the spirits within.",
      "popularity": 7.7726,
      "poster_path": "/phYEy6Am7vRlr9KzMb0wbGMHTzz.jpg",
      "release_date": "2001-07-02",
      "title": "Final Fantasy: The Spirits Within",
      "video": false,
      "vote_average": 6.198,
      "vote_count": 1488
    },
    {
      "adult": false,
      "backdrop_path": "/vBVRgryngFoqHazyLqFca6xNTeB.jpg",
      "genre_ids": [
        35,
        14,
        10749
      ],
      "id": 9722,
      "original_language": "en",
      "original_title": "Bewitched",
      "overview": "Thinking he can overshadow an unknown actress in the part, an egocentric actor unknowingly gets a witch cast in an upcoming television remake of the classic show \"Bewitched\".",
      "popularity": 8.0748,
      "poster_path": "/8lx4EXmAZo8ogh4128UBZRQfCjI.jpg",
      "release_date": "2005-06-21",
      "title": "Bewitched",
      "video": false,
      "vote_average": 5.1,
      "vote_count": 1564
    },
    {
      "adult": false,
      "backdrop_path": "/zlpKUEE4A5LjaTmEz37pw2VZQug.jpg",
      "genre_ids": [
        16,
        28,
        12,
        35,
        14,
        10749
      ],
      "id": 553835,
      "original_language": "ja",
      "original_title": "劇場版 ダンジョンに出会いを求めるのは間違っているだろうか -オリオンの矢-",
      "overview": "In the city of Orario, beneath an impossibly tall tower, lies the dungeon. Only adventurers who form partnerships with the gods themselves have any hope of defeating the monsters that lie within. But the dungeon is not the only place where monsters exist. Far from Orario, in the ruins of an ancient city, a new threat arises. To counter this threat, the goddess Artemis has come to Orario in search of a champion—but it’s not Ais Wallenstein (the legendary Sword Princess) nor Ottar (the strongest warrior to ever enter the dungeon) that she chooses. Rather it is Bell Cranel, a newbie adventurer partnered with a low-tier goddess.",
      "popularity": 7.4988,
      "poster_path": "/78x3RRydNXvdB8BhJAwZz42g1Q1.jpg",
      "release_date": "2019-02-15",
      "title": "Is It Wrong to Try to Pick Up Girls in a Dungeon?: Arrow of the Orion",
      "video": false,
      "vote_average": 7.75,
      "vote_count": 264
    },
    {
      "adult": false,
      "backdrop_path": "/uov0QRXGEaIsVGis2ttJ1ax32Kc.jpg",
      "genre_ids": [
        18,
        10749,
        14
      ],
      "id": 4688,
      "original_language": "en",
      "original_title": "Across the Universe",
      "overview": "When young dockworker Jude leaves Liverpool to find his estranged father in the United States, he is swept up by the waves of change that are re-shaping the nation. Jude falls in love with Lucy, who joins the growing anti-war movement. As the body count in Vietnam rises, political tensions at home spiral out of control and the star-crossed lovers find themselves in a psychedelic world gone mad.",
      "popularity": 7.6891,
      "poster_path": "/447c8Te3DXC46rQvDEixKGO4dS6.jpg",
      "release_date": "2007-09-14",
      "title": "Across the Universe",
      "video": false,
      "vote_average": 7.142,
      "vote_count": 1356
    },
    {
      "adult": false,
      "backdrop_path": "/3GWLfMtN9WVkabGjspBO6eihzxi.jpg",
      "genre_ids": [
        16,
        28,
        10749,
        14
      ],
      "id": 507732,
      "original_language": "ja",
      "original_title": "新妹魔王の契約者 DEPARTURES",
      "overview": "The first movie based on the TV Series The Testament of Sister New Devil, takes place right after the season 2 final.",
      "popularity": 7.6591,
      "poster_path": "/aKt2UZ8auyRGYoNMcLajmwgLxoJ.jpg",
      "release_date": "2018-01-27",
      "title": "The Testament of Sister New Devil: Departures",
      "video": false,
      "vote_average": 7.7,
      "vote_count": 36
    }
  ],
  109,
  2168,
  4,
  [
    {
      "adult": false,
      "backdrop_path": "/b0dP4lPgK8Dg0tQEPx6z73jRURA.jpg",
      "genre_ids": [
        12,
        16,
        18,
        14,
        10749
      ],
      "id": 445030,
      "original_language": "ja",
      "original_title": "ノーゲーム・ノーライフ ゼロ",
      "overview": "Six thousand years before Sora and Shiro were even a blink in the history of Disboard, war consumed the land, tearing apart the heavens, destroying stars, and even threatening to wipe out the human race. Amid the chaos and destruction, a young man named Riku leads humanity toward the tomorrow his heart believes in. One day, in the ruins of an Elf city, he meets Schwi, a female exiled \"Ex Machina\" android who asks him to teach her what it means to have a human heart.",
      "popularity": 7.0437,
      "poster_path": "/cCBB6BGRj5nCTaEgogDtkHfjOLK.jpg",
      "release_date": "2017-07-15",
      "title": "No Game No Life: Zero",
      "video": false,
      "vote_average": 7.814,
      "vote_count": 403
    },
    {
      "adult": false,
      "backdrop_path": "/gHFuLHxruielBcMEZx1WowxbRWS.jpg",
      "genre_ids": [
        14,
        35,
        10749,
        878
      ],
      "id": 9327,
      "original_language": "en",
      "original_title": "The Nutty Professor",
      "overview": "When beautiful Carla Purty joins the university faculty, genetic professor Dr. Sherman Klump grows desperate to whittle his 400-pound frame down to size and win her heart. So, with one swig of his experimental fat-reducing serum, Sherman becomes 'Buddy Love', a fast-talking, pumped-up, plumped down Don Juan.",
      "popularity": 7.7106,
      "poster_path": "/fMtb5aZoLRNbMnCkatFsTmPRfl5.jpg",
      "release_date": "1996-06-28",
      "title": "The Nutty Professor",
      "video": false,
      "vote_average": 5.637,
      "vote_count": 2956
    },
    {
      "adult": false,
      "backdrop_path": "/gg9zZB9xLPWmuxOpKw0HX0QLMN6.jpg",
      "genre_ids": [
        14,
        10749
      ],
      "id": 672647,
      "original_language": "en",
      "original_title": "The Map of Tiny Perfect Things",
      "overview": "Two teenagers trapped in an endless time loop set out to find all the tiny things that make that one day perfect.",
      "popularity": 8.0949,
      "poster_path": "/foHto5PECzIaKT4ADV9x2nWY0jg.jpg",
      "release_date": "2021-02-12",
      "title": "The Map of Tiny Perfect Things",
      "video": false,
      "vote_average": 7.117,
      "vote_count": 794
    },
    {
      "adult": false,
      "backdrop_path": "/nvz6Bu17ipOHGHpWRm3ezpE76j2.jpg",
      "genre_ids": [
        35,
        10749,
        14
      ],
      "id": 2619,
      "original_language": "en",
      "original_title": "Splash",
      "overview": "A successful businessman falls in love with the girl of his dreams. There's one big complication though; he's fallen hook, line and sinker for a mermaid.",
      "popularity": 7.2077,
      "poster_path": "/7FutTsMWBwVhjk1Ujf1wtndUVZh.jpg",
      "release_date": "1984-03-09",
      "title": "Splash",
      "video": false,
      "vote_average": 6.257,
      "vote_count": 1384
    },
    {
      "adult": false,
      "backdrop_path": "/hBbdXQyr7FWw3KRXnt3LTNt3Fzd.jpg",
      "genre_ids": [
        18,
        14,
        10749
      ],
      "id": 967941,
      "original_language": "en",
      "original_title": "Wicked: For Good",
      "overview": "With the Wizard and the entirety of Oz framing her as wicked, Elphaba’s righteous crusade comes into conflict with Glinda’s struggle for power. As a mysterious cyclone brings in an unwitting young outsider, the former friends will soon discover how much their actions have changed each other, and all of Oz, for good. The second part of a two-part feature film adaptation of the Broadway musical phenomenon.",
      "popularity": 7.5989,
      "poster_path": "/cdlwS7DF4gw9F0jadfPHptuGuCt.jpg",
      "release_date": "2025-11-19",
      "title": "Wicked: For Good",
      "video": false,
      "vote_average": 0.0,
      "vote_count": 0
    },
    {
      "adult": false,
      "backdrop_path": "/90IcDDC47Rck4D2fyZbpZ1rbFZW.jpg",
      "genre_ids": [
        18,
        14,
        10749
      ],
      "id": 556694,
      "original_language": "en",
      "original_title": "Three Thousand Years of Longing",
      "overview": "A solitary scholar discovers an ancient bottle while on a trip to Istanbul and unleashes a djinn who offers her three wishes. Filled with reluctance, she is unable to come up with one, so the djinn tries to inspire her with his stories.",
      "popularity": 7.3921,
      "poster_path": "/nS7DNl4A7XnDncZX70UJ8ALAihF.jpg",
      "release_date": "2022-08-24",
      "title": "Three Thousand Years of Longing",
      "video": false,
      "vote_average": 6.888,
      "vote_count": 1449
    },
    {
      "adult": false,
      "backdrop_path": "/6nLdSON3ErniBZTXWG7WRqs5jGz.jpg",
      "genre_ids": [
        14,
        18,
        53,
        9648,
        10749
      ],
      "id": 251,
      "original_language": "en",
      "original_title": "Ghost",
      "overview": "After a young man is murdered, his spirit stays behind to warn his lover of impending danger, with the help of a reluctant psychic.",
      "popularity": 7.2047,
      "poster_path": "/w9RaPHov8oM5cnzeE27isnFMsvS.jpg",
      "release_date": "1990-07-13",
      "title": "Ghost",
      "video": false,
      "vote_average": 7.225,
      "vote_count": 5686
    },
    {
      "adult": false,
      "backdrop_path": "/jjtA1eeiJmjc1lZla1N9Ha0CYTf.jpg",
      "genre_ids": [
        16,
        28,
        12,
        18,
        14,
        10749
      ],
      "id": 968868,
      "original_language": "ja",
      "original_title": "劇場版 美少女戦士セーラームーンCosmos 前編",
      "overview": "The Sailor Guardians enjoy a brief moment of peace until Mamoru's Golden Crystal is stolen by Sailor Galaxia and the mysterious Sailor Starlights appear. One by one, Sailor Moon’s friends and loved ones are targeted by a formidable new enemy who threatens to destroy everything and rule over the cosmos.",
      "popularity": 7.7715,
      "poster_path": "/8X3nxTHHM2HZCUhCvCzKYDeOeoL.jpg",
      "release_date": "2023-06-09",
      "title": "Pretty Guardian Sailor Moon Cosmos the Movie Part 1",
      "video": false,
      "vote_average": 7.3,
      "vote_count": 58
    },
    {
      "adult": false,
      "backdrop_path": "/fYrWYtAQoeW00vflpeVbvJjkEjb.jpg",
      "genre_ids": [
        14,
        18,
        35,
        878,
        10749
      ],
      "id": 39545,
      "original_language": "en",
      "original_title": "TiMER",
      "overview": "In this comedic fantasy, science has facilitated the search for a soul mate via biotechnological implants that count down to the moment one is supposed to meet his or her match. But Oona is worried: She's nearly 30, and her TiMER isn't ticking yet. Will her dream guy get snatched up by someone else?",
      "popularity": 6.7563,
      "poster_path": "/6UaErUBsWbqOLRaw3Dtq7QVwylf.jpg",
      "release_date": "2009-05-14",
      "title": "TiMER",
      "video": false,
      "vote_average": 6.3,
      "vote_count": 240
    },
    {
      "adult": false,
      "backdrop_path": "/Z4FW54wpXHcYKpCOY0OGhYwQ1I.jpg",
      "genre_ids": [
        16,
        14,
        28,
        10749,
        35
      ],
      "id": 30575,
      "original_language": "ja",
      "original_title": "劇場版 美少女戦士セーラームーンS 〜かぐや姫の恋人〜",
      "overview": "As Usagi and her friends enjoy Christmas vacation, an unusual and fierce snowstorm hits town... The evil Snow Queen Kaguya has returned to claim Earth as her own. Crucial to Queen Kaguya's plan is a magical crystal from outer space, approaching Earth disguised as a comet. Once she gets hold of the crystal, she will have the power to suck away all life energy and cover the Earth in ice. Will Sailor Moon find the crystal before Queen Kaguya? Will her powers be enough to save the Earth from permanent winter? All hope lies with the Legendary Ultimate Scout Power!",
      "popularity": 7.3314,
      "poster_path": "/8HLrjXHz5LhmIMiahoC3S55bSim.jpg",
      "release_date": "1994-12-04",
      "title": "Sailor Moon S the Movie: Hearts in Ice",
      "video": false,
      "vote_average": 7.679,
      "vote_count": 134
    },
    {
      "adult": false,
      "backdrop_path": "/wTvDGO0xGMmnScqjuiDeWU7PkcB.jpg",
      "genre_ids": [
        10749,
        14,
        18
      ],
      "id": 293863,
      "original_language": "en",
      "original_title": "The Age of Adaline",
      "overview": "After 29-year-old Adaline recovers from a nearly lethal accident, she inexplicably stops growing older. As the years stretch on and on, Adaline keeps her secret to herself  until she meets a man who changes her life.",
      "popularity": 6.6655,
      "poster_path": "/MbILysGhjAbnZi1Okae9wYqLMx.jpg",
      "release_date": "2015-04-16",
      "title": "The Age of Adaline",
      "video": false,
      "vote_average": 7.481,
      "vote_count": 6768
    },
    {
      "adult": false,
      "backdrop_path": "/jhxmxSNBNCAKtHeJnJhWpkOOI7d.jpg",
      "genre_ids": [
        16,
        14,
        10749,
        10402,
        10751
      ],
      "id": 28032,
      "original_language": "en",
      "original_title": "Thumbelina",
      "overview": "Born of a flower and growing to only a couple of inches tall, poor Thumbelina is worried she'll never meet someone her own size, until she happens to catch the eye of Prince Cornelius of the Fairies. Just as soon as she finds love, however, it's torn away from her when she is kidnapped by Ms. Toad. Now Thumbelina has to escape Ms. Toad's grasp and search for Prince Cornelius. Luckily, there's a whole city of animals willing to help her.",
      "popularity": 7.5167,
      "poster_path": "/eBvSSfwAKgcjF4eyaeNSzTCpfaF.jpg",
      "release_date": "1994-03-30",
      "title": "Thumbelina",
      "video": false,
      "vote_average": 6.408,
      "vote_count": 503
    },
    {
      "adult": false,
      "backdrop_path": "/8ZlxM5IYLtg2KnRl1IoS83mlxt0.jpg",
      "genre_ids": [
        35,
        14,
        10749
      ],
      "id": 23082,
      "original_language": "en",
      "original_title": "The Invention of Lying",
      "overview": "Set in a world where the concept of lying doesn't exist, a loser changes his lot when he invents lying and uses it to get ahead.",
      "popularity": 7.1587,
      "poster_path": "/clP8tDZeM9jgnqmu4VBClBDpLtS.jpg",
      "release_date": "2009-10-02",
      "title": "The Invention of Lying",
      "video": false,
      "vote_average": 6.207,
      "vote_count": 2166
    },
    {
      "adult": false,
      "backdrop_path": "/s7kvb8Q04y3WC1tDQudn68u9wC8.jpg",
      "genre_ids": [
        16,
        12,
        14,
        10749
      ],
      "id": 31347,
      "original_language": "ja",
      "original_title": "劇場版 カードキャプターさくら 封印されたカード",
      "overview": "All of the Clow Cards have been captured, and Sakura Kinomoto, the new Master of the Cards, is preparing to play the lead in the play for the town festival. However, a new evil force is causing mysterious events all over Tomoeda, including the disappearance of Sakura's cards. With Syaoran's help, Sakura must figure out the cause of these events, and save her town.",
      "popularity": 7.0451,
      "poster_path": "/xvReXWSIieGMWj0Dzh9hxtJe4Fq.jpg",
      "release_date": "2000-07-15",
      "title": "Cardcaptor Sakura: The Sealed Card",
      "video": false,
      "vote_average": 8.118,
      "vote_count": 182
    },
    {
      "adult": false,
      "backdrop_path": "/4Xyl0udmu2wVMNMasW7z728iU7O.jpg",
      "genre_ids": [
        878,
        12,
        16,
        18,
        14,
        10749,
        28
      ],
      "id": 14945,
      "original_language": "ja",
      "original_title": "銀色の髪のアギト",
      "overview": "It is 300 years into the future. Earth's environment had been devastated by mankind's own foolish plans and humankind is beleaguered by the sentient forests which they have awoken. The world balance is tipped when a young boy named Agito stumbles across a machine that glowed in a strange blue hue inside a forbidden sanctuary.",
      "popularity": 6.4361,
      "poster_path": "/deky1Av1w6wgSzcFbtcsFgrKKtV.jpg",
      "release_date": "2006-01-07",
      "title": "Origin: Spirits of the Past",
      "video": false,
      "vote_average": 6.93,
      "vote_count": 230
    },
    {
      "adult": false,
      "backdrop_path": "/iBl3hhtHC7qQX7jGphIAYLpmpPC.jpg",
      "genre_ids": [
        35,
        10749,
        16,
        14
      ],
      "id": 430214,
      "original_language": "ja",
      "original_title": "夜は短し歩けよ乙女",
      "overview": "As a group of university students go out for a night on the town, a sophomore known only as \"The Girl with Black Hair\" experiences a series of surreal encounters with the local nightlife – all the while unaware of the romantic longings of \"Senpai\", a senior student who has been creating increasingly fantastic and contrived reasons to run into her in an effort to win her heart.",
      "popularity": 6.9,
      "poster_path": "/7kmsC5N0m9aNSN2K4TSt65aseLU.jpg",
      "release_date": "2017-04-07",
      "title": "Night Is Short, Walk On Girl",
      "video": false,
      "vote_average": 7.487,
      "vote_count": 224
    },
    {
      "adult": false,
      "backdrop_path": "/3c4BQzT0sS09IA5gRtJFIgyh95b.jpg",
      "genre_ids": [
        16,
        10749,
        28,
        14
      ],
      "id": 37100,
      "original_language": "ja",
      "original_title": "劇場版 美少女戦士セーラームーンR",
      "overview": "While enjoying the flower gardens, Sailor Moon and friends encounter an old childhood friend of Mamoru's: an alien! He's come back to give Mamoru a special flower but doesn't like Usagi and the rest of the planet's inhabitants. Sailor Moon must defend the earth from the evil Kisenian Flower he's brought back... before the evil vines and blossoms overrun the planet!",
      "popularity": 6.9975,
      "poster_path": "/sOsEDVFv2dJ8sI77XzQ2SeqRObZ.jpg",
      "release_date": "1993-12-05",
      "title": "Sailor Moon R: The Movie - The Promise of the Rose",
      "video": false,
      "vote_average": 7.856,
      "vote_count": 163
    },
    {
      "adult": false,
      "backdrop_path": "/h5gSLRhquJEkXz7qmu8HhBN2x4p.jpg",
      "genre_ids": [
        16,
        14,
        9648,
        10749
      ],
      "id": 23166,
      "original_language": "ja",
      "original_title": "劇場版「空の境界」第六章 忘却録音",
      "overview": "January 1999: Apprentice mage Azaka Kokutou, Mikiya's younger sister, has been ordered by her mentor, Touko Aozaki, to investigate a certain incident in which fairies steal the memories of students at Azaka's school, Reien Academy. Azaka launches an investigation with the help of Shiki.",
      "popularity": 6.9737,
      "poster_path": "/fbZeNT66ZUsCOCOeFpL2a4zjwiN.jpg",
      "release_date": "2008-12-20",
      "title": "The Garden of Sinners: Oblivion Recording",
      "video": false,
      "vote_average": 6.8,
      "vote_count": 81
    },
    {
      "adult": false,
      "backdrop_path": "/ieTEC1HsZ69FVR6hcjdrdq3Ale5.jpg",
      "genre_ids": [
        35,
        14,
        10749
      ],
      "id": 37725,
      "original_language": "en",
      "original_title": "It's a Boy Girl Thing",
      "overview": "A visit to a natural history museum proves catastrophic for two high school rivals, an overachiever and a jock, when an ancient Aztec statue casts a spell that causes them to switch bodies and see exactly what it's like to walk in the other's shoes.",
      "popularity": 6.7965,
      "poster_path": "/9k15RI1szgavLTLTKYgxoDASjjz.jpg",
      "release_date": "2006-07-15",
      "title": "It's a Boy Girl Thing",
      "video": false,
      "vote_average": 6.529,
      "vote_count": 1047
    },
    {
      "adult": false,
      "backdrop_path": "/4epIlsVpzk2k1fuFS2pzurpIQTJ.jpg",
      "genre_ids": [
        35,
        14,
        10749
      ],
      "id": 449563,
      "original_language": "en",
      "original_title": "Isn't It Romantic",
      "overview": "For a long time, Natalie, an Australian architect living in New York City, had always believed that what she had seen in rom-coms is all fantasy. But after thwarting a mugger at a subway station only to be knocked out while fleeing, Natalie wakes up and discovers that her life has suddenly become her worst nightmare—a romantic comedy—and she is the leading lady.",
      "popularity": 6.445,
      "poster_path": "/5xNBYXuv8wqiLVDhsfqCOr75DL7.jpg",
      "release_date": "2019-02-13",
      "title": "Isn't It Romantic",
      "video": false,
      "vote_average": 6.211,
      "vote_count": 3498
    }
  ],
  109,
  2168
]
